tiled2bin/Tiled2ZX0.py
tiled2bin/__init__.py
tiled2bin/cli.py
tiled2bin/helper.py
tiled2bin/ioUser.py
tiled2zx0-0.4.dist-info/METADATA
tiled2zx0-0.4.dist-info/WHEEL
tiled2zx0-0.4.dist-info/entry_points.txt
tiled2zx0-0.4.dist-info/top_level.txt
tiled2zx0-0.4.dist-info/RECORD
