Metadata-Version: 2.4
Name: tiled2zx0
Version: 0.4
Summary: Convert tmx Tiled map to ZX0 compressed file
Home-page: https://github.com/rtorralba/tiled2zx0
Author: Raül Torralba
Dynamic: author
Dynamic: description
Dynamic: description-content-type
Dynamic: home-page
Dynamic: summary
